LICENSE
README.md
setup.cfg
setup.py
pycronius/__init__.py
pycronius/benchmark.py
pycronius/rules.py
pycronius/scheduler.py
pycronius/tests.py
pycronius/utils.py
pycronius.egg-info/PKG-INFO
pycronius.egg-info/SOURCES.txt
pycronius.egg-info/dependency_links.txt
pycronius.egg-info/top_level.txt