Metadata-Version: 2.1
Name: pycronius
Version: 0.0.2
Summary: It is a fully-tested, benchmarked utility for efficiently matching datetime objects and cron rules.
Home-page: https://github.com/themwh/pycronius
Author: The Megawatt Hour
Author-email: admin@themwh.com
License: MIT
Download-URL: https://github.com/themwh/pycronius/archive/v0.0.2.tar.gz
Keywords: python,cron,date,time,match,rule
Platform: UNKNOWN
Classifier: Intended Audience :: Developers
Classifier: License :: OSI Approved :: MIT License
Classifier: Programming Language :: Python :: 3
Classifier: Programming Language :: Python :: 3.4
Classifier: Programming Language :: Python :: 3.5
Classifier: Programming Language :: Python :: 3.6
Classifier: Programming Language :: Python :: 3.7
